petl_addons/__init__.py
petl_addons/apply.py
petl_addons-0.0.1.dist-info/METADATA
petl_addons-0.0.1.dist-info/WHEEL
petl_addons-0.0.1.dist-info/licenses/LICENSE
petl_addons-0.0.1.dist-info/RECORD
