Metadata-Version: 2.4
Name: petl_addons
Version: 0.0.1
Summary: A collection of extensions for PETL
Project-URL: Homepage, https://codeberg.org/dringtech/petl_addons
Project-URL: Issues, https://codeberg.org/dringtech/petl_addons/issues
Author-email: Giles Dring <giles@dringtech.com>
License-File: LICENSE
Classifier: License :: OSI Approved :: MIT License
Classifier: Operating System :: OS Independent
Classifier: Programming Language :: Python :: 3
Requires-Python: >=3.8
Requires-Dist: petl
